.landscape.yml
.travis.yml
AUTHORS
ChangeLog
LICENSE.txt
README.md
requirements.txt
setup.cfg
setup.py
hacks/__init__.py
hacks.egg-info/PKG-INFO
hacks.egg-info/SOURCES.txt
hacks.egg-info/dependency_links.txt
hacks.egg-info/not-zip-safe
hacks.egg-info/pbr.json
hacks.egg-info/requires.txt
hacks.egg-info/top_level.txt
tests/test_hacks_around.py
tests/test_hacks_around_nameless.py
tests/test_hacks_around_stdout.py
tests/test_hacks_before_after.py
tests/test_hacks_enter_exit.py
tests/test_hacks_into_and_call.py
tests/test_hacks_multinames.py
tests/test_hacks_on_top_of.py
tests/test_hacks_stealing.py
tests/test_hacks_up.py
tests/test_hacks_up_nameless.py