Metadata-Version: 1.1
Name: hacks
Version: 0.0.12
Summary: hacks, a Python plugin library that doesn't play by the rules
Home-page: https://github.com/t184256/hacks
Author: Alexander Sosedkin
Author-email: monk@unboiled.info
License: MIT
Keywords: plugins
Platform: UNKNOWN
Classifier: Development Status :: 2 - Pre-Alpha
Classifier: Intended Audience :: Developers
Classifier: Intended Audience :: Information Technology
Classifier: License :: OSI Approved :: MIT License
Classifier: Operating System :: OS Independent
Classifier: Programming Language :: Python
Classifier: Programming Language :: Python :: 3 :: Only
